[{"team1Name":"Rajasthan Royals","name":"Robin Uthappa ","venue":"Dubai International Cricket Stadium","date":"17 October 2020 - day (20-over match)","team2Name":"Royal Challengers Bangalore","run":"41","ball":"22","fours":"7","six":"1","sr":"186.36"},{"team2Name":"Rajasthan Royals","name":"Robin Uthappa ","venue":"Zayed Cricket Stadium, Abu Dhabi","date":"19 October 2020 - night (20-over match)","team1Name":"Chennai Super Kings","run":"4","ball":"9","fours":"0","six":"0","sr":"44.44"},{"team2Name":"Rajasthan Royals","name":"Robin Uthappa ","venue":"Sharjah Cricket Stadium","date":"27 September 2020 - night (20-over match)","team1Name":"Kings XI Punjab","run":"9","ball":"4","fours":"2","six":"0","sr":"225.00"},{"team1Name":"Rajasthan Royals","name":"Robin Uthappa ","venue":"Sharjah Cricket Stadium","date":"22 September 2020 - night (20-over match)","team2Name":"Chennai Super Kings","run":"5","ball":"9","fours":"0","six":"0","sr":"55.55"},{"team2Name":"Rajasthan Royals","name":"Robin Uthappa ","venue":"Zayed Cricket Stadium, Abu Dhabi","date":"25 October 2020 - night (20-over match)","team1Name":"Mumbai Indians","run":"13","ball":"11","fours":"2","six":"0","sr":"118.18"},{"team2Name":"Rajasthan Royals","name":"Robin Uthappa ","venue":"Zayed Cricket Stadium, Abu Dhabi","date":"30 October 2020 - night (20-over match)","team1Name":"Kings XI Punjab","run":"30","ball":"23","fours":"1","six":"2","sr":"130.43"},{"team2Name":"Rajasthan Royals","name":"Robin Uthappa ","venue":"Dubai International Cricket Stadium","date":"30 September 2020 - night (20-over match)","team1Name":"Kolkata Knight Riders","run":"2","ball":"7","fours":"0","six":"0","sr":"28.57"},{"team2Name":"Rajasthan Royals","name":"Robin Uthappa ","venue":"Dubai International Cricket Stadium","date":"01 November 2020 - night (20-over match)","team1Name":"Kolkata Knight Riders","run":"6","ball":"2","fours":"0","six":"1","sr":"300.00"},{"team2Name":"Rajasthan Royals","name":"Robin Uthappa ","venue":"Dubai International Cricket Stadium","date":"11 October 2020 - day (20-over match)","team1Name":"Sunrisers Hyderabad","run":"18","ball":"15","fours":"1","six":"1","sr":"120.00"},{"team1Name":"Rajasthan Royals","name":"Robin Uthappa ","venue":"Dubai International Cricket Stadium","date":"22 October 2020 - night (20-over match)","team2Name":"Sunrisers Hyderabad","run":"19","ball":"13","fours":"2","six":"1","sr":"146.15"},{"team2Name":"Rajasthan Royals","name":"Robin Uthappa ","venue":"Dubai International Cricket Stadium","date":"14 October 2020 - night (20-over match)","team1Name":"Delhi Capitals","run":"32","ball":"27","fours":"3","six":"1","sr":"118.51"},{"team1Name":"Rajasthan Royals","name":"Robin Uthappa ","venue":"Zayed Cricket Stadium, Abu Dhabi","date":"03 October 2020 - day (20-over match)","team2Name":"Royal Challengers Bangalore","run":"17","ball":"22","fours":"1","six":"0","sr":"77.27"}]